phase_space_chem/__init__.py
phase_space_chem/diabatization.py
phase_space_chem/grids.py
phase_space_chem/hamiltonians.py
phase_space_chem/operators.py
phase_space_chem/potentials.py
phase_space_chem/transform.py
phase_space_chem-0.1.0.dist-info/licenses/LICENSE
phase_space_chem-0.1.0.dist-info/METADATA
phase_space_chem-0.1.0.dist-info/WHEEL
phase_space_chem-0.1.0.dist-info/top_level.txt
phase_space_chem-0.1.0.dist-info/RECORD
