Metadata-Version: 2.4
Name: phase_space_chem
Version: 0.1.0
Summary: Electron Transfer, Diabatic Couplings and Vibronic Energy Gaps in a Phase Space Framework
Author-email: kuslavicek <kuslavicek@gmail.com>
License: MIT License
Project-URL: Homepage, https://github.com/kuslavicek/phase_space_chem
Project-URL: Bug Tracker, https://github.com/kuslavicek/phase_space_chem/issues
Classifier: Programming Language :: Python :: 3
Classifier: License :: OSI Approved :: MIT License
Classifier: Operating System :: OS Independent
Requires-Python: >=3.8
License-File: LICENSE
Requires-Dist: numpy
Requires-Dist: scipy
Provides-Extra: dev
Requires-Dist: pytest; extra == "dev"
Requires-Dist: check-manifest; extra == "dev"
Dynamic: license-file
